pyutilb/__init__.py
pyutilb/asyncio_apscheduler_thread.py
pyutilb/asyncio_threadpool.py
pyutilb/atomic.py
pyutilb/base_extractor.py
pyutilb/base_validator.py
pyutilb/cmd.py
pyutilb/file.py
pyutilb/lazy.py
pyutilb/log.py
pyutilb/logging.conf
pyutilb/module_loader.py
pyutilb/ocr_baidu.py
pyutilb/ocr_youdao.py
pyutilb/spark_df_proxy.py
pyutilb/stat.py
pyutilb/strs.py
pyutilb/tail.py
pyutilb/template.py
pyutilb/threadlocal.py
pyutilb/ts.py
pyutilb/util.py
pyutilb/var_parser.py
pyutilb/yaml_boot.py
pyutilb/zkfile/__init__.py
pyutilb/zkfile/filelistener.py
pyutilb/zkfile/zkchildlistener.py
pyutilb/zkfile/zkconfig.py
pyutilb/zkfile/zkconfigfiles.py
pyutilb/zkfile/zkfilesubscriber.py
pyutilb-1.0.7.dist-info/LICENSE
pyutilb-1.0.7.dist-info/METADATA
pyutilb-1.0.7.dist-info/WHEEL
pyutilb-1.0.7.dist-info/top_level.txt
pyutilb-1.0.7.dist-info/RECORD
