Metadata-Version: 2.1
Name: pyutilb
Version: 1.0.7
Summary: pyutilb: python common utilities code
Home-page: https://github.com/shigebeyond/pyutilb
Author: shigebeyond
Author-email: 772910474@qq.com
License: BSD
Classifier: Development Status :: 5 - Production/Stable
Classifier: Topic :: Software Development :: Testing
Classifier: Topic :: Software Development :: Quality Assurance
Classifier: Topic :: Software Development :: Libraries :: Python Modules
Classifier: Operating System :: POSIX :: Linux
Classifier: Operating System :: MacOS :: MacOS X
Classifier: Operating System :: Microsoft :: Windows
Classifier: Programming Language :: Python
Classifier: Programming Language :: Python :: 3.7
Classifier: Programming Language :: Python :: 3.8
Classifier: Programming Language :: Python :: 3.9
Requires-Python: >=3.6
License-File: LICENSE
Requires-Dist: PyYAML (==6.0)
Requires-Dist: jsonpath (==0.82)
Requires-Dist: lxml (==4.9.1)
Requires-Dist: requests (==2.27.1)
Requires-Dist: cssselect (==1.1.0)
Requires-Dist: query-string (==2020.12.3)
Requires-Dist: pandas (>=1.1.5)
Requires-Dist: APScheduler (==3.10.1)
Requires-Dist: kazoo (==2.9.0)
Requires-Dist: python-dotenv (==0.20.0)
Requires-Dist: Mako (==1.1.6)
